.gitignore
.travis.yml
CHANGES.txt
MANIFEST.in
README.rst
bootstrap.py
buildout.cfg
corejet.cfg
i18n.sh
setup.py
travis.cfg
src/collective/__init__.py
src/collective.pfg.dexterity.egg-info/PKG-INFO
src/collective.pfg.dexterity.egg-info/SOURCES.txt
src/collective.pfg.dexterity.egg-info/dependency_links.txt
src/collective.pfg.dexterity.egg-info/entry_points.txt
src/collective.pfg.dexterity.egg-info/namespace_packages.txt
src/collective.pfg.dexterity.egg-info/not-zip-safe
src/collective.pfg.dexterity.egg-info/requires.txt
src/collective.pfg.dexterity.egg-info/top_level.txt
src/collective/pfg/__init__.py
src/collective/pfg/dexterity/__init__.py
src/collective/pfg/dexterity/adapter.py
src/collective/pfg/dexterity/config.py
src/collective/pfg/dexterity/configure.zcml
src/collective/pfg/dexterity/interfaces.py
src/collective/pfg/dexterity/testing.py
src/collective/pfg/dexterity/testing_robot.py
src/collective/pfg/dexterity/locales/collective.pfg.dexterity.pot
src/collective/pfg/dexterity/locales/en/LC_MESSAGES/collective.pfg.dexterity.mo
src/collective/pfg/dexterity/locales/en/LC_MESSAGES/collective.pfg.dexterity.po
src/collective/pfg/dexterity/locales/fi/LC_MESSAGES/collective.pfg.dexterity.mo
src/collective/pfg/dexterity/locales/fi/LC_MESSAGES/collective.pfg.dexterity.po
src/collective/pfg/dexterity/locales/fr/LC_MESSAGES/collective.pfg.dexterity.mo
src/collective/pfg/dexterity/locales/fr/LC_MESSAGES/collective.pfg.dexterity.po
src/collective/pfg/dexterity/profiles/default/factorytool.xml
src/collective/pfg/dexterity/profiles/default/metadata.xml
src/collective/pfg/dexterity/profiles/default/propertiestool.xml
src/collective/pfg/dexterity/profiles/default/types.xml
src/collective/pfg/dexterity/profiles/default/workflows.xml
src/collective/pfg/dexterity/profiles/default/types/Dexterity_Content_Adapter.xml
src/collective/pfg/dexterity/profiles/default/types/FormFolder.xml
src/collective/pfg/dexterity/tests/__init__.py
src/collective/pfg/dexterity/tests/test_boolean.py
src/collective/pfg/dexterity/tests/test_date.py
src/collective/pfg/dexterity/tests/test_date.robot
src/collective/pfg/dexterity/tests/test_feedback.py
src/collective/pfg/dexterity/tests/test_robot.py