Metadata-Version: 1.1
Name: collective.pfg.dexterity
Version: 0.10.1
Summary: Installs dexterity content creation adapter for PloneFormGen
Home-page: https://github.com/datakurre/collective.pfg.dexterity/
Author: Asko Soukka
Author-email: asko.soukka@iki.fi
License: ZPL
Platform: UNKNOWN
Classifier: Programming Language :: Python
Classifier: Topic :: Software Development :: Libraries :: Python Modules
